fast_pagination/__init__.py
fast_pagination/models.py
fast_pagination/services.py
fast_pagination/utils.py
fastapi_lowlevel_pagination-0.0.1.dist-info/LICENSE
fastapi_lowlevel_pagination-0.0.1.dist-info/METADATA
fastapi_lowlevel_pagination-0.0.1.dist-info/WHEEL
fastapi_lowlevel_pagination-0.0.1.dist-info/top_level.txt
fastapi_lowlevel_pagination-0.0.1.dist-info/RECORD
