Metadata-Version: 2.1
Name: fastapi-lowlevel-pagination
Version: 0.0.1
Summary: A fastapi lowlevel pagination system
Home-page: https://github.com/LooLzzz/fastapi-lowlevel-pagination
Author: LooLzzz
Author-email: noaml12@hotmail.com
Project-URL: Bug Tracker, https://github.com/LooLzzz/fastapi-lowlevel-pagination/issues
Classifier: Programming Language :: Python :: 3
Classifier: License :: OSI Approved :: MIT License
Classifier: Operating System :: OS Independent
Requires-Python: >=3.6
License-File: LICENSE
Requires-Dist: fastapi
